[
  {
    "name": "MSPRequ",
    "value": "id=N&lt=1747310195&co=1",
    "domain": ".login.live.com",
    "path": "/",
    "expires": -1,
    "size": 30,
    "httpOnly": true,
    "secure": true,
    "session": true,
    "sameSite": "None",
    "sameParty": false,
    "sourceScheme": "Secure",
    "sourcePort": 443
  },
  {
    "name": "MSPOK",
    "value": "$uuid-ebd4f298-7c81-46bf-a802-4732c40d8cc1$uuid-43829deb-5b6a-45ab-8f82-d507dd0faa82$uuid-25f6bec7-fbc5-4c20-96fd-30acf87180ed$uuid-e2fcc3e8-d3ba-4288-9bc9-9e353163a9ce$uuid-bafbd1a5-ef2c-42ec-b23c-3c37a1740f4c",
    "domain": ".login.live.com",
    "path": "/",
    "expires": -1,
    "size": 215,
    "httpOnly": true,
    "secure": true,
    "session": true,
    "sameSite": "None",
    "sameParty": false,
    "sourceScheme": "Secure",
    "sourcePort": 443
  },
  {
    "name": "OParams",
    "value": "11O.Dn46J5NXwXZvQThUc65L2g4J**x70t8QomMZyaWVZsD4c0wAwsnwrM1!GvR4r5EfpTSr7WQlEFW997fCAStFxQcEoRnOpHC33btMUg0OCcUuEj1J91Ajd*hI3Fdo4F*kOFp9SDNCOiOr*vR5GGCNgo2V3Yls04cjf8llrRnve9ocpK7GG4FKnqX4LK5BMjiAR8cTHScNpOLHg597NtLm4iFT1c*IyJHhrUTuMSW0qprvSu7u8l4MJKy0VU2S55JYsPcxLsdcBwcvyhpLnJbS8x4PEnnuiarGQvsy7Ha6UNRKbDUWvnmjq4ocGhKzhg7nxw$$",
    "domain": ".login.live.com",
    "path": "/",
    "expires": -1,
    "size": 335,
    "httpOnly": true,
    "secure": true,
    "session": true,
    "sameSite": "None",
    "sameParty": false,
    "sourceScheme": "Secure",
    "sourcePort": 443
  },
  {
    "name": "MicrosoftApplicationsTelemetryDeviceId",
    "value": "71b958b1-82ad-4452-bac4-5dc6b88bc7d4",
    "domain": "login.live.com",
    "path": "/",
    "expires": 1778846225.137591,
    "size": 74,
    "httpOnly": false,
    "secure": true,
    "session": false,
    "sameSite": "None",
    "sameParty": false,
    "sourceScheme": "Secure",
    "sourcePort": 443
  },
  {
    "name": "MSFPC",
    "value": "GUID=f22dd518b1ee4c1093398bf7c6dcf550&HASH=f22d&LV=202505&V=4&LU=1747310201664",
    "domain": "login.live.com",
    "path": "/",
    "expires": 1778846205.159608,
    "size": 83,
    "httpOnly": false,
    "secure": true,
    "session": false,
    "sameSite": "None",
    "sameParty": false,
    "sourceScheme": "Secure",
    "sourcePort": 443
  },
  {
    "name": "__Host-MSAAUTH",
    "value": "11-M.C515_SN1.0.U.CkgWk!PKcG4Yc0E*LAgE6Kz5CI7j8!de76LVKY5to5rNZMMNOgSlgSLCwdOg!amhI0xHN9aZCQJ6xMKoYtqVdFfqFbZdq9wxaDG6YYvmJh!pnNqky1Mg*k0X8dUjCQ905O98dvYWv13b1ayNOMiI1espLtwDGLqDJBVXoOUhTH0pxNqqQYDgV8JEYbm1NCXdM2qknv6SG06w17E3OB9TocvZhlXsmwDqyC5vP3JGjuflDHI0bdVEyqomfcU2PKJ!SC1bwGq7R74xrrwtTgG!yeo$",
    "domain": "login.live.com",
    "path": "/",
    "expires": -1,
    "size": 312,
    "httpOnly": true,
    "secure": true,
    "session": true,
    "sameSite": "None",
    "sameParty": false,
    "sourceScheme": "Secure",
    "sourcePort": 443
  },
  {
    "name": "ai_session",
    "value": "OoAAGv0CZXm9C9V3fGTsyI|1747310197082|1747310225142",
    "domain": "login.live.com",
    "path": "/",
    "expires": 1747312025,
    "size": 60,
    "httpOnly": false,
    "secure": true,
    "session": false,
    "sameSite": "None",
    "sameParty": false,
    "sourceScheme": "Secure",
    "sourcePort": 443
  },
  {
    "name": "fptctx2",
    "value": "taBcrIH61PuCVH7eNCyH0F58uBDuZFZOunQHZt3FugkwPDMxRB3Fp2BZGUObgMx9xL6kGBzSQl7KdOkR4OLLxm%252bwWUTYdsOm0JD4DD2ezxifEfdx%252bwy9rnrwij6WL4GoypaMJsyCMgErXF5ETGM5p%252fyn68cNVvtgRddGF9pwEMEiQ%252fQVuVb5tLQ1IEagCBCT961dhrwJYkyZ5qn2K3jPZPM3%252byPr0T6DwD%252bm%252b5lgwNWHEnojUYAt4pGkZcEXmtyXXb1g4wVP%252bMouKWAlNDGJZqWAQSHPfTpEXLtspKS%252f%252fxnPpqUMcJF1qBJolxsRLc%252b6rcD5Jzp2mo2kXm8GPSfq4A%253d%253d",
    "domain": ".live.com",
    "path": "/",
    "expires": -1,
    "size": 403,
    "httpOnly": true,
    "secure": true,
    "session": true,
    "sameParty": false,
    "sourceScheme": "Secure",
    "sourcePort": 443
  },
  {
    "name": "uaid",
    "value": "a2cba6c078ee4337b8ec95be5d592988",
    "domain": ".login.live.com",
    "path": "/",
    "expires": -1,
    "size": 36,
    "httpOnly": true,
    "secure": true,
    "session": true,
    "sameSite": "None",
    "sameParty": false,
    "sourceScheme": "Secure",
    "sourcePort": 443
  },
  {
    "name": "MUID",
    "value": "7cacfc2bbb5241d5934be514d6432eb6",
    "domain": ".live.com",
    "path": "/",
    "expires": 1778846196.738273,
    "size": 36,
    "httpOnly": true,
    "secure": true,
    "session": false,
    "sameParty": false,
    "sourceScheme": "Secure",
    "sourcePort": 443
  },
  {
    "name": "PPLState",
    "value": "1",
    "domain": ".live.com",
    "path": "/",
    "expires": -1,
    "size": 9,
    "httpOnly": false,
    "secure": true,
    "session": true,
    "sameSite": "None",
    "sameParty": false,
    "sourceScheme": "Secure",
    "sourcePort": 443
  },
  {
    "name": "MSCC",
    "value": "45.45.245.77-US",
    "domain": ".login.live.com",
    "path": "/",
    "expires": 1781006196.10052,
    "size": 19,
    "httpOnly": true,
    "secure": true,
    "session": false,
    "sameSite": "None",
    "sameParty": false,
    "sourceScheme": "Secure",
    "sourcePort": 443
  }
]